{
    "nav": {
        "ul": [
            "الصفحة الرئيسية",
            "تعاون",
            "تقنيّات",
            "من نحن"
        ],
        "signIn": "تسجيل دخول",
        "joinNow": "انضم الآن"
    },
    "sliderSection": [
        {
            "h2": "مرآتك ",
            "span1": "لأبعاد جديدة",
            "p": "منصتك الإجتماعية الرّائدة ها هنا لتغيّر نظرتك عن التّواصل، التّفاعل والإبداع.إنخرط في عالم التواصل الإجتماعي ذو التّقنيات السّباقة، تمتّع بعالمك الإفتراضي في راحة يديك وأطلق العنان لمخيّلتك.",
            "img": "img1.png",
            "btn": "تميّز! إنضمَ الآن!"
        },
        {
            "h2": "اتصل، التقط",
            "span1": " وأبدع",
            "span2": "منصة تواصل إجتماعي غير مسبوقة!",
            "p": "أنشئ ملفك الشخصي واخلق بعدًا يظهر تميّزك. خصص شخصيتك ثلاثية الأبعاد، صمم مساحتك الإفتراضية كما تحبّ، التقط، شارك، اكسب الإعجاب والإحترام وعزز من حضورك الإجتماعي",
            "img": "img2.png",
            "btn": "تميّز! إنضمَ الآن!"
        },
        {
            "h2": "تخيّل، أنشئ ",
            "span1": "وتميّز",
            "span2": "أنشئ بعدك الإفتراضي وصمّمه حسب رغبتك عبر مميزات شيك شاك:",
            "img": "img3.png",
            "ul": [
                "نظام بناء مستقبلي يتيح لك الإنغماس في عالمك الخياليّ",
                "قم ببناء منزلك، محيطك أو متجرك الخاص وعدّلهم حسب تفضيلاتك",
                "شارك إبداعك مع العالم! قم بدعوة أصدقاءك أو انضم إليهم في أبعادهم الخاصة أو قم بزيارة عالم مؤثرك المفضل وتعرّف إليه"
            ],
            "btn": "تميّز! إنضمَ الآن!"
        },
        {
            "h2": "استقبل، تفاعل ",
            "span1": "واستمتع",
            "p": "قم بدعوة الأصدقاء والعائلة من جميع أنحاء العالم للإستمتاع بالأنشطة الإجتماعية المختلفة، يمكنكم استضافة أو حضور اللّقاءات والتجمعات، ممارسة الألعاب سويًّا، استكشاف العالم الإفتراض وزيارة عوالمكم الفريدة. كما يمكنكم أيضًا التّسوّق سويًّا ومشاركة تجربة تفاعلية لا مثيل لها",
            "img": "img4.png",
            "btn": "تميّز! إنضمَ الآن!"
        },
        {
            "h2": "جرّب قبل أن",
            "span1": "تشتري!",
            "p": "استمتع بتجربة التّسوّق الإجتماعي المدعومة بأحدث التقنيّات مع Check Chack تسوّق برفقة أصدقائك، تصفّح المنتجات والخدمات، قم بعرضها بنظام ال3D أو جربها في الواقع المعزز! وإن أعجبتك قم بشرائها بشكل سهل وبطريقة دفع آمنة، حيث سيتم توصيلها إلى باب منزلك",
            "img": "img5.png",
            "btn": "تميّز! إنضمَ الآن!"
        }
    ],
    "grid": [
        {
            "h3": "تعاون، ",
            "span1": "ازدهر",
            "p": "CheckChack هي المنصة المثالية لازدهار عملك، تنميّة علامتك التجارية، تحديث خدماتك، زيادة إيراداتك وتأمين الوصول إلى جمهور أوسع. توفّر CheckChack لأصحاب الأعمال ومزوّدي الخدمات لوحة القيادة الأكثر تقدمًا للتّحكم بشكل كامل وفعّال في كل جوانب الأعمال والتّجارة",
            "span2": "مهتمّ؟ تعاون معنا!",
            "a": "تميّز! إنضمَ الآن!",
            "arrow": "<span class='material-icons'>west</span>"
        },
        {
            "h3": "حقق ",
            "span1": "أهدافك",
            "ul": [
                "قم بزيادة مبيعاتك",
                "اجذب العملاء بتجربة تسوّق تفاعليّة فريدة",
                "قلل من تبديل وإعادة البضائع عبر تقنية التجربة عبر الواقع الإفتراضي",
                "وسّع حضورك على منصات التواصل الإجتماعي وسيطر على كل جوانب عملك",
                "وسّع نطاق وصول جمهورك: انضمّ إلى مراكز تسوّق شهيرة أو اختار استضافة عملك في مساحات افتراضية خاصّة بمشاهير ومؤثّرين"
            ],
            "span2": "مهتمّ؟ تعاون معنا!",
            "a": "تميّز! إنضمَ الآن!",
            "arrow": "<span class='material-icons'>west</span>"
        },
        {
            "h3": "تطوّر، ",
            "span1": "تقدّم",
            "ul": [
                "قم بتصميم وإنشاء متجرك أو مركز خدماتك",
                "إختر موقعك المفضّل، مثل مراكز التسوق الإفتراضية أو صالات العرض والمعارض وغيرها",
                "اعرض منتجاتك وخدماتك بشكل ثلاثي الأبعاد",
                "اعرض تجربة المنتجات بتنقية الواقع المعزز",
                "حمل قائمة السلّع والخدمات بنقرة زرّ",
                "رتب متجرك بحسب تفضيلاتك، اضف مكاتب المساعدة أو لافتات أو لوحات"
            ],
            "span2": "مهتمّ؟ تعاون معنا!",
            "a": "تميّز! إنضمَ الآن!",
            "arrow": "<span class='material-icons'>west</span>"
        },
        {
            "h3": "وسّع آفاقك ",
            "span1": "واستفد",
            "ul": [
                "استفد من روبوت ذاتي التّعلّم، يعتمد على الذكاء الإصطناعي للإعتناء بشؤون العملاء وتأمين حسن الأداء باستمرار",
                "قدّم خدمات عبر الإنترنت كخدمات السّفر، الحجوزات والإشتراكات",
                "أضف طرق الدفع الآمنة واربط عملك بشركات الشحن والتوصيل التي تختارها",
                "قم بتنمية علامتك التّجارية عبر حلول تسويقيّة واسعة النّطاق تشمل مساحات عامة افتراضية للخدمات الدّعائية وعرض الإعلانات"
            ],
            "span2": "مهتمّ؟ تعاون معنا!",
            "a": "تميّز! إنضمَ الآن!",
            "arrow": "<span class='material-icons'>west</span>"
        }
    ],
    "technologies": [
        {
            "h2": "تجربة المنتجات ",
            "span1": "بتقنية الواقع المعزز",
            "p": "طريقة سبّاقة لإضافة الواقعية إلى تجربة التّسوق",
            "ul": [
                "قم بإضافة أقنعة الوجه والفلاتر بتقنية الواقع المعزز على مقاطع الفيديو الخاصة بك",
                "جرّب الملابس، الأحذية، مستحضرات التبرّج، النّظارات، الأثاث وغيرها من المنتجات قبل شرائها",
                "شارك تجربة التسوّق بشكل تفاعلي مع الأصدقاء"
            ],
            "ReadMore": "تميّز! إنضمَ الآن!",
            "video1": "https://chickchack.s3.eu-west-2.amazonaws.com/new-landing-page-assets/02.mp4",
            "video2": "./assets/video/02.mp4"
        },
        {
            "h2": "الذكاء ",
            "span1": "الإصطناعي",
            "p": "ميزة دعم العملاء الأكثر تقدمًا من النّاحية التكنولوجية",
            "ul": [
                "أضف روبوتات ذاتية التّعلّم إلى متجرك",
                "إجمع البيانات التحليلية وقم بتحسين خدماتك",
                "قدّم دعم سريع، فعّال وسهل لعملائك",
                "خصص مظهر وخدمات الروبوت بحسب حاجتك ليتناسب مع علامتك التجارية واستفد منه للتسويق والبيع وخدمات أخرى"
            ],
            "ReadMore": "تميّز! إنضمَ الآن!",
            "img": "tec2.png"
        },
        {
            "h2": "لوحة القيادة",
            "p": "لوحة تحكم متطوّرة وشاملة",
            "ul": [
                "ميزة حصريّة تتيح لك إضافة نموذج منتجك بسهولة، تخصيصه وتعديله بحسب رغبتك أو اختيار نماذج من مكتبة قوالب ضخمة تناسب جميع احتياجاتك",
                "تحكّم في كل جوانب أنشطتك العمليّة",
                "حمّل مخزونك وخدماتك بشكل سريع وفعّال واعرضها بأحدث تقنيّات الأبعاد الثلاثية والواقع المعزّز",
                "رتّب وعدّل متجرك أو صالة العرض، راقب العمل بشكل مباشر وقم بالتّحديث والإدارة من أي مكان في العالم"
            ],
            "ReadMore": "تميّز! إنضمَ الآن!",
            "img": "tec3.png"
        },
        {
            "h2": "الخدمات ",
            "span1": "الإفتراضية",
            "p": "أجعل جميع أنشطتك التّجارية إفتراضية",
            "ul": [
                "استضف الأحداث، المؤتمرات، التّجمعات والحفلات الإفتراضية في بيئات قابلة للتخصيص والتّعديل بحسب الحاجة، إضافة إلى قوالب جاهزة تشمل إدارة كاملة من وراء الكواليس",
                "خدمات وحلول التجارة الالكترونية",
                "حوّل مكانك إلى عالم ثلاثي الأبعاد واقعي وتفاعلي",
                "خدمات تشمل الفنادق، العقارات، المواقع السياحية، مؤسسات التعليم وغيرها"
            ],
            "ReadMore": "تميّز! إنضمَ الآن!",
            "video1": "https://chickchack.s3.eu-west-2.amazonaws.com/new-landing-page-assets/01.mp4",
            "video2": "./assets/video/01.mp4"
        },
        {
            "h2": "المسح والتصميم ",
            "span1": "ثلاثيّ الأبعاد ",
            "p": "وكأنه الواقع الحقيقي!",
            "ul": [
                "امسح وجهك بتقنية ال3D",
                "أنشئ شخصيتك الثلاثية الأبعاد بشكل واقعي",
                "قم بمسح أي منتج واستيراده إلى نظامنا بجودات متعددة (low poly, high poly)",
                "استمتع بتجربة إجتماعية غامرة"
            ],
            "ReadMore": "تميّز! إنضمَ الآن!",
            "img": "tec5.png"
        }
    ],
    "tecController": [
        "تقنية الواقع المعزز",
        "الذكاء الاصطناعي",
        "لوحة القيادة",
        "الخدمات الافتراضية",
        "المسح ثلاثي الأبعاد"
    ],
    "about": {
        "h2": "من نحن؟",
        "p": "إتخذت CheckChack الدّور الرّيادي في تحقيق نهج إجتماعي فريد، متقدّم ومتميّز. لتحقيق هذه المهمّة الصّعبة اتجهنا للمثابرة والإبتكار عبر دمج أحدث التّقنيات كالواقع المعزّز، الواقع الإفتراضي والمسح الثلاثي الأبعاد. طموحنا أن نقدّم لكم منصّة جديرة بحضوركم"
    },
    "download": {
        "h2": "التحميل الآن!        ",
        "img1": "<img src='./assets/images/download/download2.png'alt=''>",
        "img2": "<img src='./assets/images/download/download3.png'alt=''>",
        "img3": "<img src='./assets/images/download/download1.png'alt=''>",
        "img4": "<img src='./assets/images/download/download4.png'alt=''>"
    },
    "contact": {
        "theForm": {
            "h3": "تواصل معنا",
            "h2": "ارسل رسالة",
            "p": "نحن إجتماعيون في صميمنا! تواصل معنا!",
            "email": "بريدك الإلكتروني",
            "phone": "رقم موبايلك",
            "textArea": "رسالتك",
            "btn": "ارسل الان"
        },
        "card": {
            "h2": "ابقى على تواصل",
            "p": "نحن هنا من أجلك ، فقط اتصل بنا!",
            "innerCard1": {
                "title": "بريدنا الإلكتروني",
                "e1": "info@chickchack.net",
                "e2": "info@chickchack.net"
            },
            "innerCard2": {
                "title": "الهاتف الخاص بنا",
                "e1": "+971 4 576 2549",
                "e2": "+971 4 576 2549"
            },
            "innerCard3": {
                "title": "قم بزيارتنا",
                "p": "الإمارات العربية المتحدة ، الخليج التجاري ، برج القلعة # 601"
            }
        }
    },
    "footer": {
        "col_lg_4_1": {
            "p": "CheckChack هي المنصة المثالية لتزدهر أعمالك: تنمية علامتك التجارية وتقديم خدماتك إلى المستقبل .."
        },
        "col_lg_4_2": {
            "h2": "معلومات التواصل",
            "p1": "<span>العنوان :</span>الإمارات العربية المتحدة ، الخليج التجاري ، برج القلعة # 601",
            "p2": "<span>رقم الهاتف : </span><span  dir='ltr'>+971 4 576 2549</span>",
            "p3": "<span>البريد الإلكتروني: </span>Info@chickchack.net"
        },
        "col_lg_4_3": {
            "h2": "روابط مختصرة",
            "a1": "الرئيسية",
            "a2": "تواصل معنا",
            "a3": "حول",
            "a4": "Blog",
            "a5": "سياسة الخصوصية",
            "a6": "الشروط و الأحكام"
        }
    }
}